README.md
setup.py
wrun_service.py
wrun/__init__.py
wrun/transport.py
wrun.egg-info/PKG-INFO
wrun.egg-info/SOURCES.txt
wrun.egg-info/dependency_links.txt
wrun.egg-info/top_level.txt