Metadata-Version: 1.0
Name: wrun
Version: 0.1.7
Summary: Run Remote Windows Executables
Home-page: https://github.com/depaolim/wrun
Author: Marco De Paoli
Author-email: depaolim@gmail.com
License: MIT
Platform: UNKNOWN
